Workbook

Sheet КП
B1: Заполняются только ячейки, выделенные синим цветом. Менять формулы и объемы недопустимо.
B4: Предмет тендера: | D4: Кровля подземной автостоянки в осях П24-П48
B5: Объект: | D5: Многоквартирные жилые дома со встроенными нежилыми помещениями и подземной автостоянкой, Блоки 13A и 13B
B6: Адрес объекта: | D6: г. Москва, вн.тер.г. муниципальный округ Покровское-Стрешнево, ул. Лётная, к/н 77:08:0015001:18981
B9: Наименование контрагента
B10: ИНН
B11: Адрес (юр., факт.)
A14: № п/п | B14: КОД | C14: Вид затрат | D14: Наименование затрат | E14: Примечание к расчету | F14: Ед. изм. | G14: Объем по виду работ | H14: Общий расход по материалу | I14: Цена за единицу, руб. с НДС | K14: Цена за единицу ИТОГО, руб. с НДС | L14: Стоимость ИТОГО, руб с НДС | N14: Общая стоимость, руб. с НДС | O14: Примечание участника тендера
I15: Материалы/ оборудование | J15: СМР, ПНР | L15: Материалы/ оборудование | M15: СМР, ПНР
A16: 1 | B16: 2 | C16: 3 | D16: 4 | E16: 5 | F16: 6 | G16: 7 | H16: 8 | I16: 9 | J16: 10 | K16: 11 | L16: 12 | M16: 13 | N16: 14 | O16: 15
D17: Устройство гидроизоляции кровли подземной автостоянки в осях П24-П48 | L17: =SUBTOTAL(9,L18:L79) -> 0 | M17: =SUBTOTAL(9,M18:M79) -> 0 | N17: =SUBTOTAL(9,N18:N74) -> 0
A18: 1 | D18: Устройство покрытия кровли Тип 1.1 (основная кровля) | L18: =SUBTOTAL(9,L19:L31) -> 0 | M18: =SUBTOTAL(9,M19:M31) -> 0 | N18: =SUBTOTAL(9,N19:N31) -> 0
A19: 1.1 | C19: Работа | D19: Устройство уклонообразующего слоя из керамзитобетона | F19: м3 | G19: 866.38 | I19: =SUMPRODUCT(G20:G20,I20:I20)/G19 -> 0 | J19: 0 | K19: =SUM(I19:J19) -> 0 | L19: =G19*I19 -> 0 | M19: =J19*G19 -> 0 | N19: =SUM(L19:M19) -> 0
A20: 1.1.1 | C20: Мат | D20: Керамзитобетон (керамзитовый гравий фр.20-40мм, П35, М250) | F20: м3 | G20: =G19*H20 -> 909.699 | H20: 1.05 | I20: 0
A21: 1.2 | C21: Работа | D21: Устройство стяжки толщиной 50 мм | F21: м2 | G21: 5035.44 | I21: =SUMPRODUCT(G22:G23,I22:I23)/G21 -> 0 | J21: 0 | K21: =SUM(I21:J21) -> 0 | L21: =G21*I21 -> 0 | M21: =J21*G21 -> 0 | N21: =SUM(L21:M21) -> 0
A22: 1.2.1 | C22: Мат | D22: Сетка 4Вр-1-100х100 | F22: м2 | G22: =G21*H22 -> 5538.984 | H22: 1.1 | I22: 0
A23: 1.2.2 | C23: Мат | D23: Раствор М150 | F23: м3 | G23: =G21*H23*0.05 -> 264.3606 | H23: 1.05 | I23: 0
A24: 1.3 | C24: Работа | D24: Огрунтовка поверхности | F24: м2 | G24: 5035.44 | I24: =SUMPRODUCT(G25:G25,I25:I25)/G24 -> 0 | J24: 0 | K24: =SUM(I24:J24) -> 0 | L24: =G24*I24 -> 0 | M24: =J24*G24 -> 0 | N24: =SUM(L24:M24) -> 0
A25: 1.3.1 | C25: Мат | D25: Праймер Технониколь №1 | F25: м2 | G25: =G24*H25 -> 5790.756 | H25: 1.15 | I25: 0
A26: 1.4 | C26: Работа | D26: Устройство изоляции горизонтальной в 2 слоя | F26: м2 | G26: 5035.44 | I26: =SUMPRODUCT(G27:G27,I27:I27)/G26 -> 0 | J26: 0 | K26: =SUM(I26:J26) -> 0 | L26: =G26*I26 -> 0 | M26: =J26*G26 -> 0 | N26: =SUM(L26:M26) -> 0
A27: 1.4.1 | C27: Мат | D27: Техноэласт ЭПП | F27: м2 | G27: =G26*H27*2 -> 11581.512 | H27: 1.15 | I27: 0
A28: 1.5 | C28: Работа | D28: Устройство утеплителя в 1 слой | F28: м2 | G28: 5035.44 | I28: =SUMPRODUCT(G29:G29,I29:I29)/G28 -> 0 | J28: 0 | K28: =SUM(I28:J28) -> 0 | L28: =G28*I28 -> 0 | M28: =J28*G28 -> 0 | N28: =SUM(L28:M28) -> 0
A29: 1.5.1 | C29: Мат | D29: Экструдированный пенополистирол Технониколь Carbon Prof 500 - 150 мм | F29: м2 | G29: =G28*H29 -> 5186.5032 | H29: 1.03 | I29: 0
A30: 1.6 | C30: Работа | D30: Устройство горизонтальной профилированной мембраны | F30: м2 | G30: 5035.44 | I30: =SUMPRODUCT(G31:G31,I31:I31)/G30 -> 0 | J30: 0 | K30: =SUM(I30:J30) -> 0 | L30: =G30*I30 -> 0 | M30: =J30*G30 -> 0 | N30: =SUM(L30:M30) -> 0
A31: 1.6.1 | C31: Мат | D31: Профилированная мембрана Planter geo - 10 мм | F31: м2 | G31: =G30*H31 -> 5639.6928 | H31: 1.12 | I31: 0
A32: 2 | D32: Устройство покрытия кровли Тип 1.2 (участки прилегающие к стенам и краям) | L32: =SUBTOTAL(9,L33:L47) -> 0 | M32: =SUBTOTAL(9,M33:M47) -> 0 | N32: =SUBTOTAL(9,N33:N47) -> 0
A33: 2.1 | C33: Работа | D33: Устройство уклонообразующего слоя из керамзитобетона | F33: м3 | G33: 122.74 | I33: =SUMPRODUCT(G34:G34,I34:I34)/G33 -> 0 | J33: 0 | K33: =SUM(I33:J33) -> 0 | L33: =G33*I33 -> 0 | M33: =J33*G33 -> 0 | N33: =SUM(L33:M33) -> 0
A34: 2.1.1 | C34: Мат | D34: Керамзитобетон (керамзитовый гравий фр.20-40мм, П35, М250) | F34: м3 | G34: =G33*H34 -> 128.877 | H34: 1.05 | I34: 0
A35: 2.2 | C35: Работа | D35: Устройство стяжки толщиной 50 мм | F35: м2 | G35: 697.31 | I35: =SUMPRODUCT(G36:G37,I36:I37)/G35 -> 0 | J35: 0 | K35: =SUM(I35:J35) -> 0 | L35: =G35*I35 -> 0 | M35: =J35*G35 -> 0 | N35: =SUM(L35:M35) -> 0
A36: 2.2.1 | C36: Мат | D36: Сетка 4Вр-1-100х100 | F36: м2 | G36: =G35*H36 -> 767.041 | H36: 1.1 | I36: 0
A37: 2.2.2 | C37: Мат | D37: Раствор М150 | F37: м3 | G37: =G35*H37*0.05 -> 36.608775 | H37: 1.05 | I37: 0
A38: 2.3 | C38: Работа | D38: Устройство разделительного слоя | F38: м2 | G38: 697.31 | I38: =SUMPRODUCT(G39:G39,I39:I39)/G38 -> 0 | J38: 0 | K38: =SUM(I38:J38) -> 0 | L38: =G38*I38 -> 0 | M38: =J38*G38 -> 0 | N38: =SUM(L38:M38) -> 0
A39: 2.3.1 | C39: Мат | D39: Геотекстильное полотно Технониколь 500 г/м2 | F39: м2 | G39: =G38*H39 -> 801.9065 | H39: 1.15 | I39: 0
A40: 2.4 | C40: Работа | D40: Устройство изоляции горизонтальной в 1 слой | F40: м2 | G40: 697.31 | I40: =SUMPRODUCT(G41:G41,I41:I41)/G40 -> 0 | J40: 0 | K40: =SUM(I40:J40) -> 0 | L40: =G40*I40 -> 0 | M40: =J40*G40 -> 0 | N40: =SUM(L40:M40) -> 0
A41: 2.4.1 | C41: Мат | D41: Гидроизоляционная мембрана LOGICBASE V-SL | F41: м2 | G41: =G40*H41 -> 801.9065 | H41: 1.15 | I41: 0
A42: 2.5 | C42: Работа | D42: Устройство разделительного слоя | F42: м2 | G42: 697.31 | I42: =SUMPRODUCT(G43:G43,I43:I43)/G42 -> 0 | J42: 0 | K42: =SUM(I42:J42) -> 0 | L42: =G42*I42 -> 0 | M42: =J42*G42 -> 0 | N42: =SUM(L42:M42) -> 0
A43: 2.5.1 | C43: Мат | D43: Геотекстильное полотно Технониколь 500 г/м2 | F43: м2 | G43: =G42*H43 -> 801.9065 | H43: 1.15 | I43: 0
A44: 2.6 | C44: Работа | D44: Устройство утеплителя в 1 слой | F44: м2 | G44: 697.31 | I44: =SUMPRODUCT(G45:G45,I45:I45)/G44 -> 0 | J44: 0 | K44: =SUM(I44:J44) -> 0 | L44: =G44*I44 -> 0 | M44: =J44*G44 -> 0 | N44: =SUM(L44:M44) -> 0
A45: 2.6.1 | C45: Мат | D45: Экструдированный пенополистирол Технониколь Carbon Prof 500 - 150 мм | F45: м2 | G45: =G44*H45 -> 718.2293 | H45: 1.03 | I45: 0
A46: 2.7 | C46: Работа | D46: Устройство горизонтальной профилированной мембраны | F46: м2 | G46: 697.31 | I46: =SUMPRODUCT(G47:G47,I47:I47)/G46 -> 0 | J46: 0 | K46: =SUM(I46:J46) -> 0 | L46: =G46*I46 -> 0 | M46: =J46*G46 -> 0 | N46: =SUM(L46:M46) -> 0
A47: 2.7.1 | C47: Мат | D47: Профилированная мембрана Planter geo - 10 мм | F47: м2 | G47: =G46*H47 -> 780.9872 | H47: 1.12 | I47: 0
A48: 3 | D48: Устройство покрытия кровли Тип 2 (кровля входных групп) | L48: =SUBTOTAL(9,L49:L63) -> 0 | M48: =SUBTOTAL(9,M49:M63) -> 0 | N48: =SUBTOTAL(9,N49:N63) -> 0
A49: 3.1 | C49: Работа | D49: Устройство уклонообразующего слоя из керамзитового гравия | F49: м3 | G49: 5.26 | I49: =SUMPRODUCT(G50:G50,I50:I50)/G49 -> 0 | J49: 0 | K49: =SUM(I49:J49) -> 0 | L49: =G49*I49 -> 0 | M49: =J49*G49 -> 0 | N49: =SUM(L49:M49) -> 0
A50: 3.1.1 | C50: Мат | D50: Керамзитовый гравий с фракцией 5-10 мм, плотностью М600 | F50: м3 | G50: =G49*H50 -> 5.523 | H50: 1.05 | I50: 0
A51: 3.2 | C51: Работа | D51: Устройство стяжки толщиной 50 мм | F51: м2 | G51: 97.44 | I51: =SUMPRODUCT(G52:G53,I52:I53)/G51 -> 0 | J51: 0 | K51: =SUM(I51:J51) -> 0 | L51: =G51*I51 -> 0 | M51: =J51*G51 -> 0 | N51: =SUM(L51:M51) -> 0
A52: 3.2.1 | C52: Мат | D52: Сетка 4Вр-1-100х100 | F52: м2 | G52: =G51*H52 -> 107.184 | H52: 1.1 | I52: 0
A53: 3.2.2 | C53: Мат | D53: Раствор М150 | F53: м3 | G53: =G51*H53*0.05 -> 5.1156 | H53: 1.05 | I53: 0
A54: 3.3 | C54: Работа | D54: Устройство разделительного слоя | F54: м2 | G54: 97.44 | I54: =SUMPRODUCT(G55:G55,I55:I55)/G54 -> 0 | J54: 0 | K54: =SUM(I54:J54) -> 0 | L54: =G54*I54 -> 0 | M54: =J54*G54 -> 0 | N54: =SUM(L54:M54) -> 0
A55: 3.3.1 | C55: Мат | D55: Геотекстильное полотно Технониколь 500 г/м2 | F55: м2 | G55: =G54*H55 -> 112.056 | H55: 1.15 | I55: 0
A56: 3.4 | C56: Работа | D56: Устройство изоляции горизонтальной в 1 слой | F56: м2 | G56: 97.44 | I56: =SUMPRODUCT(G57:G57,I57:I57)/G56 -> 0 | J56: 0 | K56: =SUM(I56:J56) -> 0 | L56: =G56*I56 -> 0 | M56: =J56*G56 -> 0 | N56: =SUM(L56:M56) -> 0
A57: 3.4.1 | C57: Мат | D57: Гидроизоляционная мембрана LOGICBASE V-SL | F57: м2 | G57: =G56*H57 -> 112.056 | H57: 1.15 | I57: 0
A58: 3.5 | C58: Работа | D58: Устройство разделительного слоя | F58: м2 | G58: 97.44 | I58: =SUMPRODUCT(G59:G59,I59:I59)/G58 -> 0 | J58: 0 | K58: =SUM(I58:J58) -> 0 | L58: =G58*I58 -> 0 | M58: =J58*G58 -> 0 | N58: =SUM(L58:M58) -> 0
A59: 3.5.1 | C59: Мат | D59: Геотекстильное полотно Технониколь 500 г/м2 | F59: м2 | G59: =G58*H59 -> 112.056 | H59: 1.15 | I59: 0
A60: 3.6 | C60: Работа | D60: Устройство утеплителя в 1 слой | F60: м2 | G60: 97.44 | I60: =SUMPRODUCT(G61:G61,I61:I61)/G60 -> 0 | J60: 0 | K60: =SUM(I60:J60) -> 0 | L60: =G60*I60 -> 0 | M60: =J60*G60 -> 0 | N60: =SUM(L60:M60) -> 0
A61: 3.6.1 | C61: Мат | D61: Экструдированный пенополистирол Технониколь Carbon Prof 500 - 150 мм | F61: м2 | G61: =G60*H61 -> 100.3632 | H61: 1.03 | I61: 0
A62: 3.7 | C62: Работа | D62: Устройство горизонтальной профилированной мембраны | F62: м2 | G62: 97.44 | I62: =SUMPRODUCT(G63:G63,I63:I63)/G62 -> 0 | J62: 0 | K62: =SUM(I62:J62) -> 0 | L62: =G62*I62 -> 0 | M62: =J62*G62 -> 0 | N62: =SUM(L62:M62) -> 0
A63: 3.7.1 | C63: Мат | D63: Профилированная мембрана Planter geo - 10 мм | F63: м2 | G63: =G62*H63 -> 109.1328 | H63: 1.12 | I63: 0
A64: 4 | D64: Устройство покрытия кровли Тип 3 (кровля рампы) | L64: =SUBTOTAL(9,L65:L74) -> 0 | M64: =SUBTOTAL(9,M65:M74) -> 0 | N64: =SUBTOTAL(9,N65:N74) -> 0
A65: 4.1 | C65: Работа | D65: Устройство разделительного слоя | F65: м2 | G65: 147.83 | I65: =SUMPRODUCT(G66:G66,I66:I66)/G65 -> 0 | J65: 0 | K65: =SUM(I65:J65) -> 0 | L65: =G65*I65 -> 0 | M65: =J65*G65 -> 0 | N65: =SUM(L65:M65) -> 0
A66: 4.1.1 | C66: Мат | D66: Геотекстильное полотно Технониколь 500 г/м2 | F66: м2 | G66: =G65*H66 -> 170.0045 | H66: 1.15 | I66: 0
A67: 4.2 | C67: Работа | D67: Устройство изоляции горизонтальной в 1 слой | F67: м2 | G67: 147.83 | I67: =SUMPRODUCT(G68:G68,I68:I68)/G67 -> 0 | J67: 0 | K67: =SUM(I67:J67) -> 0 | L67: =G67*I67 -> 0 | M67: =J67*G67 -> 0 | N67: =SUM(L67:M67) -> 0
A68: 4.2.1 | C68: Мат | D68: Гидроизоляционная мембрана LOGICBASE V-SL | F68: м2 | G68: =G67*H68 -> 170.0045 | H68: 1.15 | I68: 0
A69: 4.3 | C69: Работа | D69: Устройство разделительного слоя | F69: м2 | G69: 147.83 | I69: =SUMPRODUCT(G70:G70,I70:I70)/G69 -> 0 | J69: 0 | K69: =SUM(I69:J69) -> 0 | L69: =G69*I69 -> 0 | M69: =J69*G69 -> 0 | N69: =SUM(L69:M69) -> 0
A70: 4.3.1 | C70: Мат | D70: Геотекстильное полотно Технониколь 500 г/м2 | F70: м2 | G70: =G69*H70 -> 170.0045 | H70: 1.15 | I70: 0
A71: 4.4 | C71: Работа | D71: Устройство утеплителя в 1 слой | F71: м2 | G71: 147.83 | I71: =SUMPRODUCT(G72:G72,I72:I72)/G71 -> 0 | J71: 0 | K71: =SUM(I71:J71) -> 0 | L71: =G71*I71 -> 0 | M71: =J71*G71 -> 0 | N71: =SUM(L71:M71) -> 0
A72: 4.4.1 | C72: Мат | D72: Экструдированный пенополистирол Технониколь Carbon Prof 500 - 150 мм | F72: м2 | G72: =G71*H72 -> 152.2649 | H72: 1.03 | I72: 0
A73: 4.5 | C73: Работа | D73: Устройство горизонтальной профилированной мембраны | F73: м2 | G73: 147.83 | I73: =SUMPRODUCT(G74:G74,I74:I74)/G73 -> 0 | J73: 0 | K73: =SUM(I73:J73) -> 0 | L73: =G73*I73 -> 0 | M73: =J73*G73 -> 0 | N73: =SUM(L73:M73) -> 0
A74: 4.5.1 | C74: Мат | D74: Профилированная мембрана Planter geo - 10 мм | F74: м2 | G74: =G73*H74 -> 165.5696 | H74: 1.12 | I74: 0
A75: 5 | D75: Устройство кровельных воронок | L75: =SUBTOTAL(9,L76:L79) -> 0 | M75: =SUBTOTAL(9,M76:M79) -> 0 | N75: =SUBTOTAL(9,N76:N79) -> 0
A76: 4.5 | C76: Работа | D76: Монтаж кровельных воронок | F76: шт | G76: 10 | I76: =SUMPRODUCT(G77:G77,I77:I77)/G76 -> 0 | J76: 0 | K76: =SUM(I76:J76) -> 0 | L76: =G76*I76 -> 0 | M76: =J76*G76 -> 0 | N76: =SUM(L76:M76) -> 0
A77: 4.5.1 | C77: Мат | D77: Водоприемная кровельная воронка с комплектом вспомогательных материалов в соотв. с узлом 4 рабочей документации | F77: шт | G77: =G76*H77 -> 10 | H77: 1 | I77: 0
A78: 4.5 | C78: Работа | D78: Монтаж кровельных воронок с примыканием к лотку | F78: шт | G78: 9 | I78: =SUMPRODUCT(G79:G79,I79:I79)/G78 -> 0 | J78: 0 | K78: =SUM(I78:J78) -> 0 | L78: =G78*I78 -> 0 | M78: =J78*G78 -> 0 | N78: =SUM(L78:M78) -> 0
A79: 4.5.1 | C79: Мат | D79: Водоприемная кровельная воронка с комплектом вспомогательных материалов в соотв. с узлом 5 рабочей документации | F79: шт | G79: =G78*H79 -> 9 | H79: 1 | I79: 0
D80: ИТОГО с НДС | L80: =SUBTOTAL(9,L18:L79) -> 0 | M80: =SUBTOTAL(9,M18:M79) -> 0 | N80: =SUBTOTAL(9,N18:N79) -> 0
D81: в т.ч. НДС | L81: =L80/120*20 -> 0 | M81: =M80/120*20 -> 0 | N81: =N80/120*20 -> 0
A83: !!!!!! В единичных расценках должно быть учтено:
A84: 1. Оплата труда рабочих с отчислением всех налогов и сборов;
A85: 2. Оплата необходимой для выполнения работ техники, с учетом траспортировки и её хранения
A86: 3. Амортизационные отчисления на оборудование и оснастка для производства работ;
A87: 4. Все основные и вспомогательные материалы, включая материалы для устройства узлов примыкания кровли к стенам, входным группам и витражам,
A88: узлов деформационных швов, узлов сопряжения покрытий, иных швов и примыканий ( в т.ч. вертикальных) с учетом транспортировки и хранения, если иное не предусмотрено в отдельном договоре подряда;
A89: 5. Содержание инженерно-технического и административно-хозяйственного персонала;
A90: 6. Содержание временных зданий и сооружений;
A91: 7. Затраты на подготовку, оформление и сдачу исполнительной документации;
A92: 8. Затраты на проведение необходимых испытаний и опробований;
A93: 9. Затраты на возмещение потребленной электроэнергии и воды, если иное не предусмотрено в отдельном договоре подряда;
A94: 10. Затраты на организацию и содержание безопасных условий труда, соблюдение техники безопасности и нормативно-правовых актов, действующих на территории РФ;
... A102: Квалификационная и контактная информация
A103: 1 | C103: Наличие авансирования | E103: да (%) /нет | F103: да (%) /нет
A104: 2 | C104: Является ли ваша компания плательщиком НДС | E104: да/нет | F104: да /нет
A105: 3 | C105: Готовность приступить к работе по гарантийному письму | E105: да /нет | F105: да(банк) /нет
A106: 4 | C106: Срок исполнения предмета тендера | E106: мес. | F106: мес.
A107: 5 | C107: Гарантийный срок 5 лет | E107: да/нет | F107: да /нет
A108: 6 | C108: Информация о посещении объекта (были/не были), вопросы по результатам посещения | E108: были/не были да/нет | F108: были/не были да/нет
A109: 8 | C109: Готовность подписать договор в редакции Заказчика | E109: да/нет | F109: да/нет
A110: 9 | C110: Наличие СРО | E110: да (сумма) /нет | F110: да (сумма) /нет
A111: 10 | C111: Численность работающих всего / численность, планируемая для выполнения предмета тендера | E111: кол-во/кол-во | F111: кол-во/кол-во
A112: 11 | C112: Дата регистрации компании | E112: дд/мм/гг | F112: дд/мм/гг
A113: 12 | C113: Оборот за последние 3 года (указать оборот (выручку) по данным бухгалтерской отчетности за 2022/2023/2024 год) | E113: год-сумма/год-сумма/год-сумма (руб.без НДС) | F113: год-сумма/год-сумма/год-сумма (руб.без НДС) | G113: 2022 - 2023 - 2024 - руб. без НДС
A114: 13 | C114: Сайт компании | E114: ссылка | F114: ссылка
...

Sheet БСМ
B1: Базовая стоимость ресурсов (материалов)
A2: № п/п | B2: Наименование материала | C2: Ед. изм. | D2: ЦЕНА руб., с НДС/ед. с доставкой
A3: 1 | B3: 2 | C3: 3 | D3: 4
A4: 1 | B4: Керамзитобетон (керамзитовый гравий фр.20-40мм, П35, М250) | C4: м3 | D4: =_xlfn.XLOOKUP(B4,КП!D:D,КП!I:I) -> 0
A5: 2 | B5: Сетка 4Вр-1-100х100 | C5: м2 | D5: =_xlfn.XLOOKUP(B5,КП!D:D,КП!I:I) -> 0
A6: 3 | B6: Раствор М150 | C6: м3 | D6: =_xlfn.XLOOKUP(B6,КП!D:D,КП!I:I) -> 0
A7: 4 | B7: Праймер Технониколь №1 | C7: м2 | D7: =_xlfn.XLOOKUP(B7,КП!D:D,КП!I:I) -> 0
A8: 5 | B8: Техноэласт ЭПП | C8: м2 | D8: =_xlfn.XLOOKUP(B8,КП!D:D,КП!I:I) -> 0
A9: 6 | B9: Экструдированный пенополистирол Технониколь Carbon Prof 500 - 150 мм | C9: м2 | D9: =_xlfn.XLOOKUP(B9,КП!D:D,КП!I:I) -> 0
A10: 7 | B10: Профилированная мембрана Planter geo - 10 мм | C10: м2 | D10: =_xlfn.XLOOKUP(B10,КП!D:D,КП!I:I) -> 0
A11: 8 | B11: Геотекстильное полотно Технониколь 500 г/м2 | C11: м2 | D11: =_xlfn.XLOOKUP(B11,КП!D:D,КП!I:I) -> 0
A12: 9 | B12: Гидроизоляционная мембрана LOGICBASE V-SL | C12: м2 | D12: =_xlfn.XLOOKUP(B12,КП!D:D,КП!I:I) -> 0
A13: 10 | B13: Керамзитовый гравий с фракцией 5-10 мм, плотностью М600 | C13: м3 | D13: =_xlfn.XLOOKUP(B13,КП!D:D,КП!I:I) -> 0
A14: 10 | B14: Воронка кровельная водоприемная | C14: шт | D14: 0
